fermipy/__init__.py
fermipy/_version.py
fermipy/batch.py
fermipy/castro.py
fermipy/catalog.py
fermipy/config.py
fermipy/data_struct.py
fermipy/defaults.py
fermipy/docstring_utils.py
fermipy/extension.py
fermipy/fitcache.py
fermipy/fits_utils.py
fermipy/gtanalysis.py
fermipy/gtutils.py
fermipy/hpx_utils.py
fermipy/irfs.py
fermipy/lightcurve.py
fermipy/logger.py
fermipy/ltcube.py
fermipy/merge_utils.py
fermipy/model_utils.py
fermipy/plotting.py
fermipy/residmap.py
fermipy/roi_model.py
fermipy/sed.py
fermipy/sed_plotting.py
fermipy/sensitivity.py
fermipy/skymap.py
fermipy/sourcefind.py
fermipy/sourcefind_utils.py
fermipy/spectrum.py
fermipy/srcmap_utils.py
fermipy/stats_utils.py
fermipy/timing.py
fermipy/tsmap.py
fermipy/utils.py
fermipy/version.py
fermipy/wcs_utils.py
fermipy/config/logging.yaml
fermipy/data/gammamc_dif.dat
fermipy/data/models.yaml
fermipy/data/catalogs/gll_psc_8year_v5.fit
fermipy/data/catalogs/gll_psc_v08.fit
fermipy/data/catalogs/gll_psc_v14.fit
fermipy/data/catalogs/gll_psc_v14.xml
fermipy/data/catalogs/gll_psc_v16.fit
fermipy/data/catalogs/gll_psc_v16.xml
fermipy/data/catalogs/gll_psc_v17.fit
fermipy/data/catalogs/gll_psc_v18.fit
fermipy/data/catalogs/gll_psc_v19.fit
fermipy/data/catalogs/gll_psc_v20.fit
fermipy/data/catalogs/gll_psc_v20.xml
fermipy/data/catalogs/gll_psc_v27.fit
fermipy/data/catalogs/gll_psc_v29.fit
fermipy/data/catalogs/gll_psch_v08.fit
fermipy/data/catalogs/lmc_psc_v0.fit
fermipy/data/catalogs/Extended_12years/Extended_12years.txt
fermipy/data/catalogs/Extended_12years/LAT_extended_sources_12years.fits
fermipy/data/catalogs/Extended_12years/Templates/CenALobes.fits
fermipy/data/catalogs/Extended_12years/Templates/CygnusLoop.fits
fermipy/data/catalogs/Extended_12years/Templates/FornaxA.fits
fermipy/data/catalogs/Extended_12years/Templates/G279.0+1.1.fits
fermipy/data/catalogs/Extended_12years/Templates/HB9.fits
fermipy/data/catalogs/Extended_12years/Templates/HESSJ1841-055.fits
fermipy-1.2.0.dist-info/LICENSE.rst
fermipy-1.2.0.dist-info/METADATA
fermipy-1.2.0.dist-info/WHEEL
fermipy-1.2.0.dist-info/entry_points.txt
fermipy-1.2.0.dist-info/top_level.txt
fermipy-1.2.0.dist-info/RECORD
