Metadata-Version: 2.1
Name: fermipy
Version: 1.2.0
Summary: A Python package for analysis of Fermi-LAT data
Home-page: https://github.com/fermiPy/fermipy
Author: The Fermipy developers
Author-email: fermipy.developers@gmail.com
License: BSD
Classifier: Intended Audience :: Science/Research
Classifier: License :: OSI Approved :: BSD License
Classifier: Operating System :: OS Independent
Classifier: Programming Language :: Python :: 3
Classifier: Programming Language :: Python :: 3.9
Classifier: Programming Language :: Python :: Implementation :: CPython
Classifier: Topic :: Scientific/Engineering :: Astronomy
Classifier: Development Status :: 4 - Beta
License-File: LICENSE.rst
Requires-Dist: numpy (>=1.16)
Requires-Dist: pyyaml
Requires-Dist: scipy
Requires-Dist: astropy
Requires-Dist: matplotlib (>=3.3)
Requires-Dist: gammapy (>=0.18)
Requires-Dist: healpy
Requires-Dist: astropy-healpix
